LICENSE
README.md
setup.py
algtestprocess/__init__.py
algtestprocess.egg-info/PKG-INFO
algtestprocess.egg-info/SOURCES.txt
algtestprocess.egg-info/dependency_links.txt
algtestprocess.egg-info/requires.txt
algtestprocess.egg-info/top_level.txt
algtestprocess/modules/__init__.py
algtestprocess/modules/config.py
algtestprocess/modules/jcalgtest.py
algtestprocess/modules/cli/__init__.py
algtestprocess/modules/cli/base.py
algtestprocess/modules/cli/tpm/__init__.py
algtestprocess/modules/cli/tpm/base.py
algtestprocess/modules/cli/tpm/types.py
algtestprocess/modules/cli/tpm/commands/__init__.py
algtestprocess/modules/cli/tpm/commands/metadata_update.py
algtestprocess/modules/cli/tpm/commands/report_create.py
algtestprocess/modules/cli/tpm/commands/summary_create.py
algtestprocess/modules/components/__init__.py
algtestprocess/modules/components/cardlist.py
algtestprocess/modules/components/footer.py
algtestprocess/modules/components/head.py
algtestprocess/modules/components/header.py
algtestprocess/modules/components/layout.py
algtestprocess/modules/components/modal.py
algtestprocess/modules/components/simpletable.py
algtestprocess/modules/components/utils.py
algtestprocess/modules/data/__init__.py
algtestprocess/modules/data/tpm/__init__.py
algtestprocess/modules/data/tpm/enums.py
algtestprocess/modules/data/tpm/manager.py
algtestprocess/modules/data/tpm/profiles/__init__.py
algtestprocess/modules/data/tpm/profiles/base.py
algtestprocess/modules/data/tpm/profiles/cryptoprops.py
algtestprocess/modules/data/tpm/profiles/performance.py
algtestprocess/modules/data/tpm/profiles/support.py
algtestprocess/modules/data/tpm/results/__init__.py
algtestprocess/modules/data/tpm/results/base.py
algtestprocess/modules/data/tpm/results/cryptoprops.py
algtestprocess/modules/data/tpm/results/performance.py
algtestprocess/modules/data/tpm/results/support.py
algtestprocess/modules/pages/__init__.py
algtestprocess/modules/pages/comparativetable.py
algtestprocess/modules/pages/compare.py
algtestprocess/modules/pages/executiontime.py
algtestprocess/modules/pages/heatmaps.py
algtestprocess/modules/pages/page.py
algtestprocess/modules/pages/radar.py
