Metadata-Version: 2.1
Name: algtestprocess
Version: 0.1.6
Summary: A Python package for algtestprocess
Home-page: https://github.com/crocs-muni/algtest-pyprocess
Author: Tomas Jaros
Author-email: tjaros.822@gmail.com
License-File: LICENSE
